HISTORY.md
LICENSE
MANIFEST.in
README.md
pyproject.toml
django_spirit.egg-info/PKG-INFO
django_spirit.egg-info/SOURCES.txt
django_spirit.egg-info/dependency_links.txt
django_spirit.egg-info/entry_points.txt
django_spirit.egg-info/requires.txt
django_spirit.egg-info/top_level.txt
spirit/__init__.py
spirit/middleware.py
spirit/urls.py
spirit/admin/__init__.py
spirit/admin/apps.py
spirit/admin/forms.py
spirit/admin/tests.py
spirit/admin/urls.py
spirit/admin/views.py
spirit/admin/locale/de/LC_MESSAGES/django.mo
spirit/admin/locale/de/LC_MESSAGES/django.po
spirit/admin/locale/en/LC_MESSAGES/django.mo
spirit/admin/locale/en/LC_MESSAGES/django.po
spirit/admin/locale/es/LC_MESSAGES/django.mo
spirit/admin/locale/es/LC_MESSAGES/django.po
spirit/admin/locale/fr/LC_MESSAGES/django.mo
spirit/admin/locale/fr/LC_MESSAGES/django.po
spirit/admin/locale/hu/LC_MESSAGES/django.mo
spirit/admin/locale/hu/LC_MESSAGES/django.po
spirit/admin/locale/it/LC_MESSAGES/django.mo
spirit/admin/locale/it/LC_MESSAGES/django.po
spirit/admin/locale/ky/LC_MESSAGES/django.mo
spirit/admin/locale/ky/LC_MESSAGES/django.po
spirit/admin/locale/lt/LC_MESSAGES/django.mo
spirit/admin/locale/lt/LC_MESSAGES/django.po
spirit/admin/locale/pl/LC_MESSAGES/django.mo
spirit/admin/locale/pl/LC_MESSAGES/django.po
spirit/admin/locale/pl_PL/LC_MESSAGES/django.mo
spirit/admin/locale/pl_PL/LC_MESSAGES/django.po
spirit/admin/locale/ru/LC_MESSAGES/django.mo
spirit/admin/locale/ru/LC_MESSAGES/django.po
spirit/admin/locale/sv/LC_MESSAGES/django.mo
spirit/admin/locale/sv/LC_MESSAGES/django.po
spirit/admin/locale/tr/LC_MESSAGES/django.mo
spirit/admin/locale/tr/LC_MESSAGES/django.po
spirit/admin/locale/zh_Hans/LC_MESSAGES/django.mo
spirit/admin/locale/zh_Hans/LC_MESSAGES/django.po
spirit/admin/templates/spirit/admin/_nav_menu.html
spirit/admin/templates/spirit/admin/config_basic.html
spirit/admin/templates/spirit/admin/dashboard.html
spirit/category/__init__.py
spirit/category/apps.py
spirit/category/managers.py
spirit/category/models.py
spirit/category/tests.py
spirit/category/urls.py
spirit/category/views.py
spirit/category/admin/__init__.py
spirit/category/admin/apps.py
spirit/category/admin/forms.py
spirit/category/admin/tests.py
