Metadata-Version: 2.4
Name: django-spirit
Version: 0.14.3
Summary: Spirit is a Python based forum powered by Django.
Author-email: Esteban Castro Borsani <ecastroborsani@gmail.com>
License: MIT License
Project-URL: Documentation, https://spirit.readthedocs.io
Project-URL: Source, https://github.com/nitely/Spirit
Project-URL: Donate, https://ko-fi.com/nitely_
Classifier: Development Status :: 5 - Production/Stable
Classifier: Environment :: Web Environment
Classifier: Framework :: Django
Classifier: Intended Audience :: Developers
Classifier: License :: OSI Approved :: MIT License
Classifier: Operating System :: OS Independent
Classifier: Programming Language :: Python
Classifier: Programming Language :: Python :: 3
Classifier: Topic :: Internet :: WWW/HTTP
Classifier: Topic :: Internet :: WWW/HTTP :: Dynamic Content
Requires-Python: >=3.9
Requires-Dist: Django<6,>=4.2
Requires-Dist: django-haystack~=3.3
Requires-Dist: whoosh==2.7.4
Requires-Dist: mistune==0.8.4
Requires-Dist: Pillow>=11
Requires-Dist: olefile==0.47
Requires-Dist: django-infinite-scroll-pagination~=1.3
Requires-Dist: django-djconfig~=0.11
Requires-Dist: tzdata
Provides-Extra: files
Requires-Dist: python-magic==0.4.27; extra == "files"
Requires-Dist: python-magic-bin==0.4.14; sys_platform == "win32" and extra == "files"
Provides-Extra: huey
Requires-Dist: huey~=2.5; extra == "huey"
Provides-Extra: celery
Requires-Dist: celery[redis]~=5.4; extra == "celery"
